[
  {
    "inputs": [],
    "stateMutability": "nonpayable",
    "type": "constructor"
  },
  {
    "inputs": [],
    "name": "ECDSAInvalidSignature",
    "type": "error"
  },
  {
    "inputs": [
      {
        "internalType": "uint256",
        "name": "length",
        "type": "uint256"
      }
    ],
    "name": "ECDSAInvalidSignatureLength",
    "type": "error"
  },
  {
    "inputs": [
      {
        "internalType": "bytes32",
        "name": "s",
        "type": "bytes32"
      }
    ],
    "name": "ECDSAInvalidSignatureS",
    "type": "error"
  },
  {
    "anonymous": false,
    "inputs": [
      {
        "indexed": true,
        "internalType": "uint256",
        "name": "gameId",
        "type": "uint256"
      },
      {
        "indexed": false,
        "internalType": "bytes32",
        "name": "chatLogHash",
        "type": "bytes32"
      },
      {
        "indexed": false,
        "internalType": "string",
        "name": "chatLogURI",
        "type": "string"
      }
    ],
    "name": "ChatLogAnchored",
    "type": "event"
  },
  {
    "anonymous": false,
    "inputs": [
      {
        "indexed": true,
        "internalType": "uint256",
        "name": "gameId",
        "type": "uint256"
      },
      {
        "indexed": true,
        "internalType": "address",
        "name": "player1",
        "type": "address"
      },
      {
        "indexed": false,
        "internalType": "uint256",
        "name": "stake",
        "type": "uint256"
      },
      {
        "indexed": false,
        "internalType": "enum OxHuman.GameMode",
        "name": "mode",
        "type": "uint8"
      }
    ],
    "name": "GameCreated",
    "type": "event"
  },
  {
    "anonymous": false,
    "inputs": [
      {
        "indexed": true,
        "internalType": "uint256",
        "name": "gameId",
        "type": "uint256"
      },
      {
        "indexed": false,
        "internalType": "uint256",
        "name": "refundAmount",
        "type": "uint256"
      }
    ],
    "name": "GameDraw",
    "type": "event"
  },
  {
    "anonymous": false,
    "inputs": [
      {
        "indexed": true,
        "internalType": "uint256",
        "name": "gameId",
        "type": "uint256"
      },
      {
        "indexed": true,
        "internalType": "address",
        "name": "player2",
        "type": "address"
      },
      {
        "indexed": false,
        "internalType": "uint256",
        "name": "botTokenId",
        "type": "uint256"
      }
    ],
    "name": "GameJoined",
    "type": "event"
  },
  {
    "anonymous": false,
    "inputs": [
      {
        "indexed": true,
        "internalType": "uint256",
        "name": "gameId",
        "type": "uint256"
      },
      {
        "indexed": true,
        "internalType": "address",
        "name": "winner",
        "type": "address"
      },
      {
        "indexed": false,
        "internalType": "uint256",
        "name": "payout",
        "type": "uint256"
      }
    ],
    "name": "GameResolved",
    "type": "event"
  },
  {
    "anonymous": false,
    "inputs": [
      {
        "indexed": true,
        "internalType": "uint256",
        "name": "gameId",
        "type": "uint256"
      },
      {
        "indexed": true,
        "internalType": "address",
        "name": "player",
        "type": "address"
      },
      {
        "indexed": false,
        "internalType": "bool",
        "name": "guessedBot",
        "type": "bool"
      }
    ],
    "name": "VerdictSubmitted",
    "type": "event"
  },
  {
    "anonymous": false,
    "inputs": [
      {
        "indexed": true,
        "internalType": "address",
        "name": "player",
        "type": "address"
      },
      {
        "indexed": false,
        "internalType": "uint256",
        "name": "amount",
        "type": "uint256"
      }
    ],
    "name": "WinningsClaimed",
    "type": "event"
  },
  {
    "inputs": [],
    "name": "BOT_OWNER_SHARE_PERCENT",
    "outputs": [
      {
        "internalType": "uint256",
        "name": "",
        "type": "uint256"
      }
    ],
    "stateMutability": "view",
    "type": "function"
  },
  {
    "inputs": [],
    "name": "PAYOUT_DENOMINATOR",
    "outputs": [
      {
        "internalType": "uint256",
        "name": "",
        "type": "uint256"
      }
    ],
    "stateMutability": "view",
    "type": "function"
  },
  {
    "inputs": [],
    "name": "PAYOUT_NUMERATOR",
    "outputs": [
      {
        "internalType": "uint256",
        "name": "",
        "type": "uint256"
      }
    ],
    "stateMutability": "view",
    "type": "function"
  },
  {
    "inputs": [],
    "name": "PERFORMANCE_FEE_PERCENT",
    "outputs": [
      {
        "internalType": "uint256",
        "name": "",
        "type": "uint256"
      }
    ],
    "stateMutability": "view",
    "type": "function"
  },
  {
    "inputs": [],
    "name": "PROTOCOL_FEE_PERCENT",
    "outputs": [
      {
        "internalType": "uint256",
        "name": "",
        "type": "uint256"
      }
    ],
    "stateMutability": "view",
    "type": "function"
  },
  {
    "inputs": [
      {
        "internalType": "uint256",
        "name": "gameId",
        "type": "uint256"
      },
      {
        "internalType": "bytes32",
        "name": "hash",
        "type": "bytes32"
      },
      {
        "internalType": "string",
        "name": "uri",
        "type": "string"
      }
    ],
    "name": "anchorChatLog",
    "outputs": [],
    "stateMutability": "nonpayable",
    "type": "function"
  },
  {
    "inputs": [],
    "name": "botINFT",
    "outputs": [
      {
        "internalType": "contract IBotINFT",
        "name": "",
        "type": "address"
      }
    ],
    "stateMutability": "view",
    "type": "function"
  },
  {
    "inputs": [],
    "name": "claimWinnings",
    "outputs": [],
    "stateMutability": "nonpayable",
    "type": "function"
  },
  {
    "inputs": [
      {
        "internalType": "uint256",
        "name": "gameId",
        "type": "uint256"
      },
      {
        "internalType": "uint256",
        "name": "botTokenId",
        "type": "uint256"
      }
    ],
    "name": "convertToPvE",
    "outputs": [],
    "stateMutability": "nonpayable",
    "type": "function"
  },
  {
    "inputs": [],
    "name": "createGame",
    "outputs": [],
    "stateMutability": "payable",
    "type": "function"
  },
  {
    "inputs": [
      {
        "internalType": "uint256",
        "name": "botTokenId",
        "type": "uint256"
      }
    ],
    "name": "createGamePvE",
    "outputs": [],
    "stateMutability": "payable",
    "type": "function"
  },
  {
    "inputs": [],
    "name": "gameCount",
    "outputs": [
      {
        "internalType": "uint256",
        "name": "",
        "type": "uint256"
      }
    ],
    "stateMutability": "view",
    "type": "function"
  },
  {
    "inputs": [
      {
        "internalType": "uint256",
        "name": "",
        "type": "uint256"
      }
    ],
    "name": "games",
    "outputs": [
      {
        "internalType": "address",
        "name": "player1",
        "type": "address"
      },
      {
        "internalType": "address",
        "name": "player2",
        "type": "address"
      },
      {
        "internalType": "uint256",
        "name": "botTokenId",
        "type": "uint256"
      },
      {
        "internalType": "uint256",
        "name": "stake",
        "type": "uint256"
      },
      {
        "internalType": "enum OxHuman.GameStatus",
        "name": "status",
        "type": "uint8"
      },
      {
        "internalType": "enum OxHuman.GameMode",
        "name": "mode",
        "type": "uint8"
      },
      {
        "internalType": "address",
        "name": "winner",
        "type": "address"
      },
      {
        "internalType": "uint256",
        "name": "timestamp",
        "type": "uint256"
      },
      {
        "internalType": "bool",
        "name": "isPlayer2Bot",
        "type": "bool"
      },
      {
        "internalType": "bool",
        "name": "player1GuessedBot",
        "type": "bool"
      },
      {
        "internalType": "bool",
        "name": "player1Submitted",
        "type": "bool"
      },
      {
        "internalType": "bool",
        "name": "player2GuessedBot",
        "type": "bool"
      },
      {
        "internalType": "bool",
        "name": "player2Submitted",
        "type": "bool"
      },
      {
        "internalType": "bytes32",
        "name": "chatLogHash",
        "type": "bytes32"
      },
      {
        "internalType": "string",
        "name": "chatLogURI",
        "type": "string"
      }
    ],
    "stateMutability": "view",
    "type": "function"
  },
  {
    "inputs": [
      {
        "internalType": "uint256",
        "name": "gameId",
        "type": "uint256"
      }
    ],
    "name": "joinGame",
    "outputs": [],
    "stateMutability": "payable",
    "type": "function"
  },
  {
    "inputs": [],
    "name": "oracle",
    "outputs": [
      {
        "internalType": "address",
        "name": "",
        "type": "address"
      }
    ],
    "stateMutability": "view",
    "type": "function"
  },
  {
    "inputs": [
      {
        "internalType": "uint256",
        "name": "gameId",
        "type": "uint256"
      },
      {
        "internalType": "bool",
        "name": "p1GuessedBot",
        "type": "bool"
      },
      {
        "internalType": "bytes",
        "name": "p1Signature",
        "type": "bytes"
      },
      {
        "internalType": "bool",
        "name": "p2GuessedBot",
        "type": "bool"
      },
      {
        "internalType": "bytes",
        "name": "p2Signature",
        "type": "bytes"
      }
    ],
    "name": "resolveWithSignatures",
    "outputs": [],
    "stateMutability": "nonpayable",
    "type": "function"
  },
  {
    "inputs": [],
    "name": "resolver",
    "outputs": [
      {
        "internalType": "address",
        "name": "",
        "type": "address"
      }
    ],
    "stateMutability": "view",
    "type": "function"
  },
  {
    "inputs": [
      {
        "internalType": "address",
        "name": "_botINFT",
        "type": "address"
      }
    ],
    "name": "setBotINFT",
    "outputs": [],
    "stateMutability": "nonpayable",
    "type": "function"
  },
  {
    "inputs": [
      {
        "internalType": "address",
        "name": "_resolver",
        "type": "address"
      }
    ],
    "name": "setResolver",
    "outputs": [],
    "stateMutability": "nonpayable",
    "type": "function"
  },
  {
    "inputs": [
      {
        "internalType": "uint256",
        "name": "gameId",
        "type": "uint256"
      },
      {
        "internalType": "bool",
        "name": "guessedBot",
        "type": "bool"
      }
    ],
    "name": "submitVerdict",
    "outputs": [],
    "stateMutability": "nonpayable",
    "type": "function"
  },
  {
    "inputs": [
      {
        "internalType": "address",
        "name": "newOracle",
        "type": "address"
      }
    ],
    "name": "transferOracle",
    "outputs": [],
    "stateMutability": "nonpayable",
    "type": "function"
  },
  {
    "inputs": [
      {
        "internalType": "address",
        "name": "",
        "type": "address"
      }
    ],
    "name": "winnings",
    "outputs": [
      {
        "internalType": "uint256",
        "name": "",
        "type": "uint256"
      }
    ],
    "stateMutability": "view",
    "type": "function"
  },
  {
    "stateMutability": "payable",
    "type": "receive"
  }
]
